Metadata-Version: 2.1
Name: detik-scrapper
Version: 1.0.6
Summary: Detik Scrapping
Home-page: https://sipaling.top
Author: Kiyora
Author-email: dev@sipaling.top
License: MIT
Keywords: detik scraping,scrapper
Platform: UNKNOWN
Classifier: Development Status :: 5 - Production/Stable
Classifier: Intended Audience :: Developers
Classifier: License :: OSI Approved :: MIT License
Classifier: Programming Language :: Python :: 3.9
Classifier: Programming Language :: Python :: 3 :: Only
Classifier: Topic :: Software Development :: Libraries :: Python Modules
License-File: LICENSE
